baekjoon/boj.py
baekjoon/problem.py
baekjoon/solvedac.py
baekjoon/user.py
boj/user.py
baekjoon-1.0.8.dist-info/METADATA
baekjoon-1.0.8.dist-info/WHEEL
baekjoon-1.0.8.dist-info/top_level.txt
baekjoon-1.0.8.dist-info/RECORD
